[
  {
    "name": "Chrome Lance",
	"tags": ["ore", "paralysis", "hidden"],
	"rarity": 6,
    "itemType": "Weapon",
    "weaponType": "Lance",
    "baseAttack": 414,
    "maxSharpness": "Blue",
    "baseAffinityPercent": 0,
    "ailment": "Paralysis",
    "ailmentBaseAttack": 270,
    "ailmentHidden": true,
    "slots": [
      {
        "level": 1
      },
      {
        "level": 1
      }
    ],
    "id": 123
  },
  {
    "name": "Perdition's Hand",
	"tags": ["nergigante", "dragon"],
	"rarity": 8,
    "itemType": "Weapon",
    "weaponType": "Lance",
    "baseAttack": 483,
    "maxSharpness": "Blue",
    "baseAffinityPercent": 0,
    "element": "Dragon",
    "elementBaseAttack": 150,
    "elementAttackIncreaseCapOverride": 0.33,
    "elderseal": "High",
    "slots": [
      {
        "level": 1
      }
    ],
    "id": 124
  },
  {
    "name": "Legiana Halberd II",
	"tags": ["legiana", "ice"],
	"rarity": 7,
    "itemType": "Weapon",
    "weaponType": "Lance",
    "baseAttack": 368,
    "maxSharpness": "White",
    "baseAffinityPercent": 0,
    "element": "Ice",
    "elementBaseAttack": 360,
    "id": 125,
    "slots": []
  },
  {
    "name": "Kula Hasta III",
	"tags": ["kulu-ya-ku", "sleep", "hidden"],
	"rarity": 6,
    "itemType": "Weapon",
    "weaponType": "Lance",
    "baseAttack": 391,
    "maxSharpness": "Blue",
    "baseAffinityPercent": 25,
    "ailment": "Sleep",
    "ailmentBaseAttack": 360,
    "ailmentHidden": true,
    "id": 126,
    "slots": []
  },
  {
    "name": "Gama Pilebunker II",
	"tags": ["dodogama", "blast"],
	"rarity": 7,
    "itemType": "Weapon",
    "weaponType": "Lance",
    "baseAttack": 391,
    "maxSharpness": "Blue",
    "baseAffinityPercent": 0,
    "ailment": "Blast",
    "ailmentBaseAttack": 210,
    "slots": [
      {
        "level": 2
      },
      {
        "level": 2
      }
    ],
    "id": 127
  },
  {
    "name": "Lightning Spire III",
	"tags": ["tobi-kadachi", "thunder"],
	"rarity": 6,
    "itemType": "Weapon",
    "weaponType": "Lance",
    "baseAttack": 414,
    "maxSharpness": "Blue",
    "baseAffinityPercent": 0,
    "element": "Thunder",
    "elementBaseAttack": 240,
    "slots": [
      {
        "level": 2
      }
    ],
    "id": 128
  },
  {
    "name": "Datura Pike III",
	"tags": ["pukei-pukei", "poison"],
	"rarity": 6,
    "itemType": "Weapon",
    "weaponType": "Lance",
    "baseAttack": 391,
    "maxSharpness": "Blue",
    "baseAffinityPercent": 0,
    "ailment": "Poison",
    "ailmentBaseAttack": 540,
    "slots": [
      {
        "level": 2
      },
      {
        "level": 2
      }
    ],
    "id": 129
  },
  {
    "name": "Blue Prominence",
	"tags": ["rathalos", "fire"],
	"rarity": 8,
    "itemType": "Weapon",
    "weaponType": "Lance",
    "baseAttack": 437,
    "maxSharpness": "Blue",
    "baseAffinityPercent": 20,
    "element": "Fire",
    "elementBaseAttack": 300,
    "slots": [
      {
        "level": 1
      }
    ],
    "id": 130
  },
  {
    "name": "Heavy Bone Lance II",
	"tags": ["bone", "poison", "hidden"],
	"rarity": 6,
    "itemType": "Weapon",
    "weaponType": "Lance",
    "baseAttack": 437,
    "maxSharpness": "Blue",
    "baseAffinityPercent": 0,
    "ailment": "Poison",
    "ailmentBaseAttack": 240,
    "ailmentHidden": true,
    "baseDefense": 10,
    "slots": [
      {
        "level": 3
      }
    ],
    "id": 131
  },
  {
    "name": "Love's Sorrow",
	"tags": ["vaal", "hazak", "dragon"],
	"rarity": 8,
    "itemType": "Weapon",
    "weaponType": "Lance",
    "baseAttack": 460,
    "maxSharpness": "Blue",
    "baseAffinityPercent": 0,
    "element": "Dragon",
    "elementBaseAttack": 270,
    "elderseal": "Average",
    "slots": [
      {
        "level": 2
      }
    ],
    "id": 132
  },
  {
    "name": "Dark Stinger III",
	"tags": ["hornetaur", "blast", "hidden"],
	"rarity": 6,
    "itemType": "Weapon",
    "weaponType": "Lance",
    "baseAttack": 368,
    "maxSharpness": "White",
    "baseAffinityPercent": 0,
    "ailment": "Blast",
    "ailmentBaseAttack": 240,
    "ailmentHidden": true,
    "slots": [
      {
        "level": 3
      }
    ],
    "id": 133
  },
  {
    "name": "Barroth Stinger III",
	"tags": ["barroth", "paralysis", "hidden"],
	"rarity": 6,
    "itemType": "Weapon",
    "weaponType": "Lance",
    "baseAttack": 460,
    "maxSharpness": "Blue",
    "baseAffinityPercent": -20,
    "ailment": "Paralysis",
    "ailmentBaseAttack": 390,
    "ailmentHidden": true,
    "baseDefense": 15,
    "slots": [
      {
        "level": 2
      },
      {
        "level": 1
      }
    ],
    "id": 134
  },
  {
    "name": "Garon Dhara II",
	"tags": ["odogaron", "fire", "hidden"],
	"rarity": 7,
    "itemType": "Weapon",
    "weaponType": "Lance",
    "baseAttack": 391,
    "maxSharpness": "White",
    "baseAffinityPercent": 30,
    "element": "Fire",
    "elementBaseAttack": 210,
    "elementHidden": true,
    "id": 135,
    "slots": []
  },
  {
    "name": "Water Spike III",
	"tags": ["jyuratodus", "water"],
	"rarity": 6,
    "itemType": "Weapon",
    "weaponType": "Lance",
    "baseAttack": 437,
    "maxSharpness": "Blue",
    "baseAffinityPercent": 0,
    "element": "Water",
    "elementBaseAttack": 300,
    "slots": [
      {
        "level": 2
      }
    ],
    "id": 136
  },
  {
    "name": "Dragonbone Lance III",
	"tags": ["dragonbone", "dragon"],
	"rarity": 6,
    "itemType": "Weapon",
    "weaponType": "Lance",
    "baseAttack": 368,
    "maxSharpness": "Blue",
    "baseAffinityPercent": 0,
    "element": "Dragon",
    "elementBaseAttack": 420,
    "elderseal": "Low",
    "slots": [
      {
        "level": 1
      },
      {
        "level": 1
      }
    ],
    "id": 137
  },
  {
    "name": "Bazel Myniad Rookslayer",
	"tags": ["bazelgeuse", "blast"],
	"rarity": 8,
    "itemType": "Weapon",
    "weaponType": "Lance",
    "baseAttack": 460,
    "maxSharpness": "Blue",
    "baseAffinityPercent": -10,
    "ailment": "Blast",
    "ailmentBaseAttack": 210,
    "id": 138,
    "slots": []
  },
  {
    "name": "Thunderpiercer",
	"tags": ["kirin", "thunder"],
	"rarity": 8,
    "itemType": "Weapon",
    "weaponType": "Lance",
    "baseAttack": 368,
    "maxSharpness": "Blue",
    "baseAffinityPercent": 10,
    "element": "Thunder",
    "elementBaseAttack": 540,
    "id": 139,
    "slots": []
  },
  {
    "name": "Daora's Fang",
	"tags": ["blacksteel", "kushala", "daora", "ice"],
	"rarity": 8,
    "itemType": "Weapon",
    "weaponType": "Lance",
    "baseAttack": 414,
    "maxSharpness": "Blue",
    "baseAffinityPercent": 10,
    "element": "Ice",
    "elementBaseAttack": 240,
    "slots": [
      {
        "level": 2
      }
    ],
    "id": 140
  },
  {
    "name": "Xeno Zauta",
	"tags": ["xeno'jiva", "dragon"],
	"rarity": 8,
    "itemType": "Weapon",
    "weaponType": "Lance",
    "baseAttack": 391,
    "maxSharpness": "White",
    "baseAffinityPercent": 15,
    "element": "Dragon",
    "elementBaseAttack": 180,
    "elderseal": "High",
    "slots": [
      {
        "level": 3
      },
      {
        "level": 3
      }
    ],
    "id": 141
  },
  {
    "name": "Elder Babel Spear",
	"tags": ["workshop", "fire", "hidden"],
	"rarity": 8,
    "itemType": "Weapon",
    "weaponType": "Lance",
    "baseAttack": 460,
    "maxSharpness": "Blue",
    "baseAffinityPercent": 0,
    "element": "Fire",
    "elementBaseAttack": 330,
    "elementHidden": true,
    "baseDefense": 20,
    "slots": [
      {
        "level": 3
      }
    ],
    "id": 142
  },
  {
    "name": "Fiendish Tower",
	"tags": ["deviljho", "dragon"],
	"rarity": 7,
    "itemType": "Weapon",
    "weaponType": "Lance",
    "baseAttack": 529,
    "maxSharpness": "Blue",
    "baseAffinityPercent": -25,
    "element": "Dragon",
    "elementBaseAttack": 210,
    "elderseal": "High",
    "id": 280,
    "slots": []
  }
]